criticus/__about__.py
criticus/__init__.py
criticus/__main__.py
criticus/criticus.sqlite3
criticus/gui.py
criticus/manage.py
criticus/py/__init__.py
criticus/py/ce_config.py
criticus/py/check_for_updates.py
criticus/py/combine_xml.py
criticus/py/edit_settings.py
criticus/py/mureq.py
criticus/py/txt_from_json.py
criticus/py/analyze_collation/analyze_collation_ui.py
criticus/py/analyze_collation/find_agreements.py
criticus/py/cbgm_interface/clean_xml.py
criticus/py/cbgm_interface/open_cbgm_api.py
criticus/py/cbgm_interface/open_cbgm_ui.py
criticus/py/export_to_docx/template.docx
criticus/py/export_to_docx/xml_to_docx.py
criticus/py/md2tei/MarkdownTEI.py
criticus/py/md2tei/__init__.py
criticus/py/md2tei/markdown_to_tei.py
criticus/py/md2tei/md_tei_extension.py
criticus/py/reformat_collation/__init__.py
criticus/py/reformat_collation/clean_wits.py
criticus/py/reformat_collation/differentiate_subreading_ids.py
criticus/py/reformat_collation/itsee_to_open_cbgm.py
criticus/py/reformat_collation/reformat_xml.py
criticus/py/tei2json/__init__.py
criticus/py/tei2json/edit_regex.py
criticus/py/tei2json/from_tei.py
criticus/py/tei2json/tei_to_json.py
criticus/py/tei2json/to_json.py
criticus/py/txt2json/__init__.py
criticus/py/txt2json/convert_text_to_json.py
criticus/resources/__init__.py
criticus/resources/criticus.icns
criticus/resources/criticus.ico
criticus/resources/criticus.png
criticus/resources/header.xml
criticus/resources/tei_transcription.xsl
criticus/resources/template.xml
criticus/static/css/bootstrap.min.css
criticus/static/js/_hyperscript.min.js
criticus/static/js/bootstrap.min.js
criticus/static/js/htmx.min.js
criticus/static/js/popper.min.js
criticus/staticfiles/staticfiles.json
criticus/staticfiles/admin/css/autocomplete.css
criticus/staticfiles/admin/css/autocomplete.css.gz
criticus/staticfiles/admin/css/autocomplete.d24f10bdee41.css
criticus/staticfiles/admin/css/autocomplete.d24f10bdee41.css.gz
criticus/staticfiles/admin/css/base.08e8df8c3104.css
criticus-2.0.2.dist-info/METADATA
criticus-2.0.2.dist-info/WHEEL
criticus-2.0.2.dist-info/licenses/LICENSE
criticus-2.0.2.dist-info/RECORD
